{
  "variableForMetar": "METAR",
  "moments": [
    {
      "night" : 7200,
      "dawn" : 23400,
      "day" : 54000,
      "evening" : 68400
    }
  ],
  "targets": [
    {
      "version": "night-real",
      "realweather": true,
      "time": 7200,
      "moment": "night"
    },
    {
      "version": "dawn-real",
      "realweather": true,
      "time": 23400,
      "moment": "dawn"
    },
    {
      "version": "dawn-scattered",
      "weatherfile": "scattered-1.lua",
      "time": 23400,
      "moment": "dawn"
    },
    {
      "version": "dawn-broken",
      "weatherfile": "broken-1.lua",
      "time": 23400,
      "moment": "dawn"
    },
    {
      "version": "dawn-overcast",
      "weatherfile": "overcast-1.lua",
      "time": 23400,
      "moment": "dawn"
    },
    {
      "version": "dawn-overcast-rain",
      "weatherfile": "overcast-rain-1.lua",
      "time": 23400,
      "moment": "dawn"
    },
    
	{
      "version": "day-real",
      "realweather": true,
      "time": 54000,
      "moment": "day"
    },
    {
      "version": "day-scattered",
      "weatherfile": "scattered-1.lua",
      "time": 54000,
      "moment": "day"
    },
    {
      "version": "day-broken",
      "weatherfile": "broken-1.lua",
      "time": 54000,
      "moment": "day"
    },
    {
      "version": "day-overcast",
      "weatherfile": "overcast-1.lua",
      "time": 54000,
      "moment": "day"
    },
    {
      "version": "day-overcast-rain",
      "weatherfile": "overcast-rain-1.lua",
      "time": 54000,
      "moment": "day"
    },

    {
      "version": "evening-real",
      "realweather": true,
      "time": 68400,
      "moment": "evening"
    },
    {
      "version": "evening-scattered",
      "weatherfile": "scattered-1.lua",
      "time": 68400,
      "moment": "evening"
    },
    {
      "version": "evening-broken",
      "weatherfile": "broken-1.lua",
      "time": 68400,
      "moment": "evening"
    },
    {
      "version": "evening-overcast",
      "weatherfile": "overcast-1.lua",
      "time": 68400,
      "moment": "evening"
    },
    {
      "version": "evening-overcast-rain",
      "weatherfile": "overcast-rain-1.lua",
      "time": 68400,
      "moment": "evening"
    }
  ]
}